{
    "likedRestaurants": [],
    "dislikedRestaurants": [{
        "wishList": [],
        "restaurantName": "lkjjl",
        "restaurantRating": 1,
        "isLiked": false,
        "reviewNumber": 2,
        "triedFoods": [{
            "foodRating": 1,
            "isTried": true,
            "price": 3,
            "FoodName": "hjk"
        }]
    }],
    "allRestaurants": [{
        "wishList": [],
        "restaurantName": "lkjjl",
        "restaurantRating": 1,
        "isLiked": false,
        "reviewNumber": 2,
        "triedFoods": [{
            "foodRating": 1,
            "isTried": true,
            "price": 3,
            "FoodName": "hjk"
        }]
    }]
}